odoo/addons/l10n_fi_banks/README.rst
odoo/addons/l10n_fi_banks/__init__.py
odoo/addons/l10n_fi_banks/__manifest__.py
odoo/addons/l10n_fi_banks/data/res_bank.xml
odoo/addons/l10n_fi_banks/i18n/fi.po
odoo/addons/l10n_fi_banks/i18n/l10n_fi_banks.pot
odoo/addons/l10n_fi_banks/readme/CONFIGURE.md
odoo/addons/l10n_fi_banks/readme/CONTRIBUTORS.md
odoo/addons/l10n_fi_banks/readme/CREDITS.md
odoo/addons/l10n_fi_banks/readme/DESCRIPTION.md
odoo/addons/l10n_fi_banks/readme/HISTORY.md
odoo/addons/l10n_fi_banks/readme/MAINTAINER.rst
odoo/addons/l10n_fi_banks/static/description/icon.png
odoo/addons/l10n_fi_banks/static/description/index.html
odoo/addons/l10n_fi_banks/tests/__init__.py
odoo/addons/l10n_fi_banks/tests/test_l10n_fi_banks.py
odoo_addon_l10n_fi_banks-19.0.1.0.0.2.dist-info/METADATA
odoo_addon_l10n_fi_banks-19.0.1.0.0.2.dist-info/WHEEL
odoo_addon_l10n_fi_banks-19.0.1.0.0.2.dist-info/top_level.txt
odoo_addon_l10n_fi_banks-19.0.1.0.0.2.dist-info/RECORD
